ipyexperiments/__init__.py
ipyexperiments/cell_logger.py
ipyexperiments/ipyexperiments.py
ipyexperiments/version.py
ipyexperiments/utils/__init__.py
ipyexperiments/utils/ipython.py
ipyexperiments/utils/mem.py
ipyexperiments/utils/pynvml_gate.py
ipyexperiments-0.1.29.dist-info/AUTHORS.md
ipyexperiments-0.1.29.dist-info/LICENSE.txt
ipyexperiments-0.1.29.dist-info/METADATA
ipyexperiments-0.1.29.dist-info/WHEEL
ipyexperiments-0.1.29.dist-info/top_level.txt
ipyexperiments-0.1.29.dist-info/RECORD
