Metadata-Version: 2.1
Name: ipyexperiments
Version: 0.1.29
Summary: jupyter/ipython experiment containers for GPU+CPU memory profiling, re-use and memory leaks detection.
Home-page: https://github.com/stas00/ipyexperiments
Author: Stas Bekman
Author-email: stas@stason.org
License: Apache License 2.0
Keywords: ipyexperiments,jupyter,ipython,memory,gpu,memory profiler
Classifier: Development Status :: 4 - Beta
Classifier: Intended Audience :: Developers
Classifier: License :: OSI Approved :: Apache Software License
Classifier: Natural Language :: English
Classifier: Programming Language :: Python :: 3.6
Classifier: Programming Language :: Python :: 3.7
Classifier: Programming Language :: Python :: 3.8
Classifier: Programming Language :: Python :: 3.9
Classifier: Programming Language :: Python :: 3.10
Classifier: Programming Language :: Python :: 3.11
Requires-Python: >=3.6
License-File: LICENSE.txt
License-File: AUTHORS.md
Requires-Dist: ipython
Requires-Dist: pynvml
Requires-Dist: psutil
Requires-Dist: ipython >=6.0.0
Requires-Dist: pynvx >=1.0.0 ; platform_system == "Darwin"
Provides-Extra: dev
Requires-Dist: ipython ; extra == 'dev'
Requires-Dist: pynvml ; extra == 'dev'
Requires-Dist: psutil ; extra == 'dev'
Requires-Dist: ipython >=6.0.0 ; extra == 'dev'
Requires-Dist: pynvx >=1.0.0 ; (platform_system == "Darwin") and extra == 'dev'
Provides-Extra: testing
Requires-Dist: pytest ; extra == 'testing'
Requires-Dist: nbmake ; extra == 'testing'
